odoo/addons/stock_vertical_lift_empty_tray_check/README.rst
odoo/addons/stock_vertical_lift_empty_tray_check/__init__.py
odoo/addons/stock_vertical_lift_empty_tray_check/__manifest__.py
odoo/addons/stock_vertical_lift_empty_tray_check/i18n/stock_vertical_lift_empty_tray_check.pot
odoo/addons/stock_vertical_lift_empty_tray_check/models/__init__.py
odoo/addons/stock_vertical_lift_empty_tray_check/models/res_config_settings.py
odoo/addons/stock_vertical_lift_empty_tray_check/models/vertical_lift_operation_pick.py
odoo/addons/stock_vertical_lift_empty_tray_check/models/vertical_lift_operation_pick_zero_check.py
odoo/addons/stock_vertical_lift_empty_tray_check/readme/CONFIGURE.rst
odoo/addons/stock_vertical_lift_empty_tray_check/readme/CONTRIBUTORS.rst
odoo/addons/stock_vertical_lift_empty_tray_check/readme/DESCRIPTION.rst
odoo/addons/stock_vertical_lift_empty_tray_check/security/ir.model.access.csv
odoo/addons/stock_vertical_lift_empty_tray_check/static/description/icon.png
odoo/addons/stock_vertical_lift_empty_tray_check/static/description/index.html
odoo/addons/stock_vertical_lift_empty_tray_check/tests/__init__.py
odoo/addons/stock_vertical_lift_empty_tray_check/tests/test_pick.py
odoo/addons/stock_vertical_lift_empty_tray_check/views/res_config_setting_views.xml
odoo/addons/stock_vertical_lift_empty_tray_check/views/vertical_lift_operation_pick_zero_check_views.xml
odoo14_addon_stock_vertical_lift_empty_tray_check-14.0.1.0.2.dist-info/METADATA
odoo14_addon_stock_vertical_lift_empty_tray_check-14.0.1.0.2.dist-info/WHEEL
odoo14_addon_stock_vertical_lift_empty_tray_check-14.0.1.0.2.dist-info/top_level.txt
odoo14_addon_stock_vertical_lift_empty_tray_check-14.0.1.0.2.dist-info/RECORD
